saldo-0.1.3.dist-info/METADATA
saldo-0.1.3.dist-info/WHEEL
saldo-0.1.3.dist-info/entry_points.txt
saldo-0.1.3.dist-info/licenses/LICENSE
saldo/__init__.py
saldo/config/__init__.py
saldo/config/consts.py
saldo/config/schemas.py
saldo/data/retention_tax_tables/2023/2023-01-01_2023-12-31/CAS1+DEF.json
saldo/data/retention_tax_tables/2023/2023-01-01_2023-12-31/CAS1.json
saldo/data/retention_tax_tables/2023/2023-01-01_2023-12-31/CAS1D+DEF.json
saldo/data/retention_tax_tables/2023/2023-01-01_2023-12-31/CAS1D.json
saldo/data/retention_tax_tables/2023/2023-01-01_2023-12-31/CAS2D+DEF.json
saldo/data/retention_tax_tables/2023/2023-01-01_2023-12-31/CAS2D.json
saldo/data/retention_tax_tables/2023/2023-01-01_2023-12-31/SOLCAS2+DEF.json
saldo/data/retention_tax_tables/2023/2023-01-01_2023-12-31/SOLCAS2.json
saldo/data/retention_tax_tables/2023/2023-01-01_2023-12-31/SOLD+DEF.json
saldo/data/retention_tax_tables/2023/2023-01-01_2023-12-31/SOLD.json
saldo/data/retention_tax_tables/2024/acores/2024-01-01_2024-08-31/CAS1+DEF.json
saldo/data/retention_tax_tables/2024/acores/2024-01-01_2024-08-31/CAS1.json
saldo/data/retention_tax_tables/2024/acores/2024-01-01_2024-08-31/CAS2D+DEF.json
saldo/data/retention_tax_tables/2024/acores/2024-01-01_2024-08-31/SOLCAS2+DEF.json
saldo/data/retention_tax_tables/2024/acores/2024-01-01_2024-08-31/SOLCAS2.json
saldo/data/retention_tax_tables/2024/acores/2024-01-01_2024-08-31/SOLD+DEF.json
saldo/data/retention_tax_tables/2024/acores/2024-01-01_2024-08-31/SOLD.json
saldo/data/retention_tax_tables/2024/acores/2024-09-01_2024-10-31/CAS1+DEF.json
saldo/data/retention_tax_tables/2024/acores/2024-09-01_2024-10-31/CAS1.json
saldo/data/retention_tax_tables/2024/acores/2024-09-01_2024-10-31/CAS2D+DEF.json
saldo/data/retention_tax_tables/2024/acores/2024-09-01_2024-10-31/SOLCAS2+DEF.json
saldo/data/retention_tax_tables/2024/acores/2024-09-01_2024-10-31/SOLCAS2.json
saldo/data/retention_tax_tables/2024/acores/2024-09-01_2024-10-31/SOLD+DEF.json
saldo/data/retention_tax_tables/2024/acores/2024-09-01_2024-10-31/SOLD.json
saldo/data/retention_tax_tables/2024/acores/2024-11-01_2024-12-31/CAS1+DEF.json
saldo-0.1.3.dist-info/RECORD
