Metadata-Version: 2.1
Name: saldo
Version: 0.1.3
Summary: net income calculator for Portugal
Author: Francisco Macedo
Author-Email: Francisco Macedo <franciscovcbm@gmail.com>
License: MIT
Classifier: License :: OSI Approved :: Apache Software License
Project-URL: Homepage, https://github.com/franciscobmacedo/saldo
Project-URL: Changelog, https://github.com/franciscobmacedo/saldo/releases
Project-URL: Issues, https://github.com/franciscobmacedo/saldo/issues
Project-URL: CI, https://github.com/franciscobmacedo/saldo/actions
Requires-Python: >=3.11
Provides-Extra: test
Requires-Dist: pytest; extra == "test"
Provides-Extra: dev
Requires-Dist: ruff; extra == "dev"
Requires-Dist: mypy; extra == "dev"
Requires-Dist: pre-commit; extra == "dev"
